plum/__init__.py
plum/_version.py
plum/alias.py
plum/autoreload.py
plum/dispatcher.py
plum/function.py
plum/method.py
plum/overload.py
plum/parametric.py
plum/promotion.py
plum/py.typed
plum/repr.py
plum/resolver.py
plum/signature.py
plum/type.py
plum/util.py
plum_dispatch-2.6.1.dist-info/METADATA
plum_dispatch-2.6.1.dist-info/WHEEL
plum_dispatch-2.6.1.dist-info/licenses/LICENCE.txt
plum_dispatch-2.6.1.dist-info/RECORD
