Metadata-Version: 2.4
Name: plum-dispatch
Version: 2.6.1
Summary: Multiple dispatch in Python
Project-URL: repository, https://github.com/beartype/plum
Project-URL: documentation, https://beartype.github.io/plum
Author-email: Wessel Bruinsma <wessel.p.bruinsma@gmail.com>
License: MIT
License-File: LICENCE.txt
Keywords: multiple dispatch
Classifier: Development Status :: 5 - Production/Stable
Classifier: License :: OSI Approved :: MIT License
Classifier: Operating System :: OS Independent
Classifier: Programming Language :: Python :: 3
Classifier: Typing :: Typed
Requires-Python: >=3.10
Requires-Dist: beartype>=0.16.2
Requires-Dist: rich>=10.0
Requires-Dist: typing-extensions>=4.9.0
